README.txt
buildout.cfg
setup.py
src/zc/__init__.py
src/zc.catalogqueue.egg-info/PKG-INFO
src/zc.catalogqueue.egg-info/SOURCES.txt
src/zc.catalogqueue.egg-info/dependency_links.txt
src/zc.catalogqueue.egg-info/entry_points.txt
src/zc.catalogqueue.egg-info/namespace_packages.txt
src/zc.catalogqueue.egg-info/not-zip-safe
src/zc.catalogqueue.egg-info/requires.txt
src/zc.catalogqueue.egg-info/top_level.txt
src/zc/catalogqueue/CHANGES.txt
src/zc/catalogqueue/CatalogEventQueue.py
src/zc/catalogqueue/README.txt
src/zc/catalogqueue/__init__.py
src/zc/catalogqueue/interfaces.py
src/zc/catalogqueue/queue.py
src/zc/catalogqueue/queue.txt
src/zc/catalogqueue/tests/__init__.py
src/zc/catalogqueue/tests/test_CatalogEventQueue.py
src/zc/catalogqueue/tests/test_queue.py